firstpy/__init__.py
stevenmeng_first_py-0.1.1.dist-info/METADATA
stevenmeng_first_py-0.1.1.dist-info/WHEEL
stevenmeng_first_py-0.1.1.dist-info/top_level.txt
stevenmeng_first_py-0.1.1.dist-info/RECORD
