Metadata-Version: 2.1
Name: stevenmeng-first-py
Version: 0.1.1
Summary: A brief description of my package
Home-page: https://github.com/yourusername/your-repo
Author: stevenmeng
Author-email: stevenmeng987@gmail.com
Classifier: Programming Language :: Python :: 3
Classifier: License :: OSI Approved :: MIT License
Classifier: Operating System :: OS Independent
Requires-Python: >=3.6
